aws/__init__.py
email_aws_sdk-0.1.0.dist-info/METADATA
email_aws_sdk-0.1.0.dist-info/WHEEL
email_aws_sdk-0.1.0.dist-info/top_level.txt
email_aws_sdk-0.1.0.dist-info/RECORD
