Metadata-Version: 2.4
Name: email-aws-sdk
Version: 0.1.0
Summary: Custom AWS SDK wrapper over boto3
Author: Smit Vekariya
Requires-Python: >=3.13.9
Requires-Dist: boto3>=1.40.60
Dynamic: author
Dynamic: description-content-type
Dynamic: requires-dist
Dynamic: requires-python
Dynamic: summary
